{
  "project_info": {
    "project_number": "873917801307",
    "project_id": "auth-with-f04eb",
    "storage_bucket": "auth-with-f04eb.appspot.com"
  },
  "client": [
    {
      "client_info": {
        "mobilesdk_app_id": "1:873917801307:android:27dd61934d01c54cc7307e",
        "android_client_info": {
          "package_name": "com.gotraffic"
        }
      },
      "oauth_client": [
        {
          "client_id": "873917801307-vcmtgrb5spibhfe3u8cfifs67cg23j4j.apps.googleusercontent.com",
          "client_type": 1,
          "android_info": {
            "package_name": "com.gotraffic",
            "certificate_hash": "526e563360fd817914a7fa0b4861b6bf4243b9a9"
          }
        },
        {
          "client_id": "873917801307-htf3r1tg2ndc9eqoq685d20f9099cqgj.apps.googleusercontent.com",
          "client_type": 3
        }
      ],
      "api_key": [
        {
          "current_key": "AIzaSyCe-klrybP-EUJZ5j99xWNPdm56gU1TVDI"
        }
      ],
      "services": {
        "appinvite_service": {
          "other_platform_oauth_client": [
            {
              "client_id": "873917801307-htf3r1tg2ndc9eqoq685d20f9099cqgj.apps.googleusercontent.com",
              "client_type": 3
            }
          ]
        }
      }
    }
  ],
  "configuration_version": "1"
}